{
    "key": "group_5ea7f78f94ca5",
    "title": "Artistes",
    "fields": [
        {
            "key": "field_5ea7f79a126f1",
            "label": "Date",
            "name": "show_date",
            "type": "text",
            "instructions": "",
            "required": 0,
            "conditional_logic": 0,
            "wrapper": {
                "width": "",
                "class": "",
                "id": ""
            },
            "default_value": "2020 › ...",
            "placeholder": "",
            "prepend": "",
            "append": "",
            "maxlength": ""
        },
        {
            "key": "field_5ea7f803126f2",
            "label": "Nationailté",
            "name": "show_name",
            "type": "text",
            "instructions": "",
            "required": 0,
            "conditional_logic": 0,
            "wrapper": {
                "width": "",
                "class": "",
                "id": ""
            },
            "default_value": "",
            "placeholder": "Tournée \"Panorama\"",
            "prepend": "",
            "append": "",
            "maxlength": ""
        },
        {
            "key": "field_5eb01b11d4f48",
            "label": "Colaboration Passé",
            "name": "is-past-collab",
            "type": "true_false",
            "instructions": "",
            "required": 0,
            "conditional_logic": 0,
            "wrapper": {
                "width": "",
                "class": "",
                "id": ""
            },
            "message": "",
            "default_value": 0,
            "ui": 0,
            "ui_on_text": "",
            "ui_off_text": ""
        }
    ],
    "location": [
        [
            {
                "param": "post_type",
                "operator": "==",
                "value": "artist"
            }
        ]
    ],
    "menu_order": 0,
    "position": "acf_after_title",
    "style": "default",
    "label_placement": "top",
    "instruction_placement": "label",
    "hide_on_screen": [
        "excerpt",
        "discussion",
        "comments",
        "author",
        "format",
        "categories",
        "send-trackbacks"
    ],
    "active": 1,
    "description": "",
    "modified": 1588600289
}